nlp_dict/__init__.py
nlp_dict/nlp_dict.py
nlp_dict/resources/dict.json
nlp_dict-0.1.2.dist-info/AUTHORS.rst
nlp_dict-0.1.2.dist-info/LICENSE
nlp_dict-0.1.2.dist-info/METADATA
nlp_dict-0.1.2.dist-info/WHEEL
nlp_dict-0.1.2.dist-info/top_level.txt
nlp_dict-0.1.2.dist-info/RECORD
