Metadata-Version: 2.1
Name: nlp-dict
Version: 0.1.2
Summary: Chinese Dictionary for NLP
Home-page: https://github.com/howl-anderson/nlp_dict
Author: Xiaoquan Kong
Author-email: u1mail2me@gmail.com
License: Apache Software License 2.0
Keywords: nlp_dict
Platform: UNKNOWN
Classifier: Development Status :: 2 - Pre-Alpha
Classifier: Intended Audience :: Developers
Classifier: License :: OSI Approved :: Apache Software License
Classifier: Natural Language :: English
Classifier: Programming Language :: Python :: 3
Classifier: Programming Language :: Python :: 3.5
Classifier: Programming Language :: Python :: 3.6
Classifier: Programming Language :: Python :: 3.7
Classifier: Programming Language :: Python :: 3.8
Requires-Python: >=3.5
Requires-Dist: nlp-utils
